{"stat.crouchOneCm":1,"stat.damageDealt":251585,"achievement.exploreAllBiomes":{"value":0,"progress":["Desert","Ocean","Beach"]},"stat.killEntity.Bat":417,"achievement.openInventory":3,"stat.mineBlock.minecraft.sand":3,"stat.fallOneCm":6980,"stat.useItem.minecraft.diamond_sword":2361,"stat.flyOneCm":22221,"stat.damageTaken":1428,"stat.entityKilledBy.Creeper":1,"stat.timeSinceDeath":2031,"stat.killEntity.Enderman":17,"stat.leaveGame":1,"stat.useItem.minecraft.golden_apple":2,"stat.diveOneCm":443,"stat.killEntity.Creeper":261,"stat.killEntity.Villager":1,"stat.playOneMinute":19209,"stat.killEntity.Spider":73,"stat.killEntity.Slime":16,"stat.entityKilledBy.Skeleton":1,"stat.jump":113,"stat.deaths":4,"stat.swimOneCm":4310,"stat.killEntity.Witch":12,"stat.mobKills":1510,"stat.killEntity.Skeleton":177,"stat.entityKilledBy.Enderman":1,"stat.killEntity.Squid":161,"stat.walkOneCm":206981,"stat.killEntity.Zombie":183,"stat.sprintOneCm":53}